asjs.py
asjs-0.1.3.dist-info/LICENSE
asjs-0.1.3.dist-info/METADATA
asjs-0.1.3.dist-info/WHEEL
asjs-0.1.3.dist-info/RECORD
