Metadata-Version: 2.1
Name: asjs
Version: 0.1.3
Summary: Python module for implement object with syntax from JavaScript
Home-page: https://github.com/tankalxat34/asjs
License: MIT
Keywords: js,javascript,datatype
Author: Alexander Podstrechnyy
Author-email: tankalxat34@gmail.com
Requires-Python: >=3.8,<4.0
Classifier: License :: OSI Approved :: MIT License
Classifier: Programming Language :: Python :: 3
Classifier: Programming Language :: Python :: 3.8
Classifier: Programming Language :: Python :: 3.9
Classifier: Programming Language :: Python :: 3.10
Classifier: Programming Language :: Python :: 3.11
Project-URL: Repository, https://github.com/tankalxat34/asjs
